README.rst
setup.py
alpaca/__init__.py
alpaca/algebra.py
alpaca/ensembl.py
alpaca/peek.py
alpaca/polish_notation.py
alpaca/prototype.py
alpaca/s_expressions.py
alpaca/utils.py
alpaca/vcf.py
alpaca/version.py
alpaca/caller/__init__.py
alpaca/caller/annotate.py
alpaca/caller/calls.py
alpaca/index/__init__.py
alpaca/index/global_index.py
alpaca/index/pileup.py
alpaca/index/sample_index.py
alpaca/index/utils.py
alpaca/index/version.py
alpaca/index/view.py
alpaca/show/footer.html
alpaca/show/header.html
alpaca/show/show_html.py
alpaca/show/show_json.py
alpaca_variant_caller.egg-info/PKG-INFO
alpaca_variant_caller.egg-info/SOURCES.txt
alpaca_variant_caller.egg-info/dependency_links.txt
alpaca_variant_caller.egg-info/entry_points.txt
alpaca_variant_caller.egg-info/not-zip-safe
alpaca_variant_caller.egg-info/requires.txt
alpaca_variant_caller.egg-info/top_level.txt