Metadata-Version: 1.1
Name: alpaca-variant-caller
Version: 0.3.3
Summary: An algebraic parallel SNV caller using OpenCL
Home-page: https://alpaca.readthedocs.org
Author: Johannes Köster
Author-email: johannes.koester@tu-dortmund.de
License: MIT
Platform: UNKNOWN
Classifier: Development Status :: 5 - Production/Stable
Classifier: Environment :: Console
Classifier: Intended Audience :: Science/Research
Classifier: License :: OSI Approved :: MIT License
Classifier: Natural Language :: English
Classifier: Programming Language :: Python :: 3
Classifier: Topic :: Scientific/Engineering :: Bio-Informatics
